MANIFEST.in
README.md
dev-requirements.txt
requirements.txt
setup.py
test-requirements.txt
docs/.DS_Store
docs/extra.css
docs/index.md
docs/contributing/contributing.md
docs/fields/basic_field.md
docs/fields/checkbox_field.md
docs/fields/checkboxes_field.md
docs/fields/dropdown_field.md
docs/fields/email_field.md
docs/fields/hidden_field.md
docs/fields/html_field.md
docs/fields/multi_line_field.md
docs/fields/multi_select_field.md
docs/fields/number_field.md
docs/fields/radio_field.md
docs/fields/url_field.md
docs/getting_started/installing.md
docs/getting_started/out_of_the_box.md
docs/getting_started/using_your_own_page_models.md
docs/screenshots/.DS_Store
docs/screenshots/custom-form-builder-page.png
docs/screenshots/waf-form-fields.png
docs/screenshots/fields/waf-basic-field.png
docs/screenshots/fields/waf-checkbox-field.png
docs/screenshots/fields/waf-checkboxes-field.png
docs/screenshots/fields/waf-dropdown-field.png
docs/screenshots/fields/waf-hidden-field.png
docs/screenshots/fields/waf-html-field.png
docs/screenshots/fields/waf-multiline-field.png
docs/screenshots/fields/waf-multiselect-field.png
docs/screenshots/fields/waf-number-field.png
docs/screenshots/fields/waf-radio-field.png
docs/usage/settings.md
wagtail_advanced_form_builder/__init__.py
wagtail_advanced_form_builder/apps.py
wagtail_advanced_form_builder/constants.py
wagtail_advanced_form_builder/utils.py
wagtail_advanced_form_builder/wagtail_hooks.py
wagtail_advanced_form_builder.egg-info/PKG-INFO
wagtail_advanced_form_builder.egg-info/SOURCES.txt
wagtail_advanced_form_builder.egg-info/dependency_links.txt
wagtail_advanced_form_builder.egg-info/not-zip-safe
wagtail_advanced_form_builder.egg-info/requires.txt
wagtail_advanced_form_builder.egg-info/top_level.txt
wagtail_advanced_form_builder/blocks/__init__.py
wagtail_advanced_form_builder/blocks/base_static_block.py
wagtail_advanced_form_builder/blocks/inline_form_block.py
wagtail_advanced_form_builder/blocks/fields/__init__.py
wagtail_advanced_form_builder/blocks/fields/base_field_block.py
wagtail_advanced_form_builder/blocks/fields/blank_condition_block.py
wagtail_advanced_form_builder/blocks/fields/checkbox_field_block.py
wagtail_advanced_form_builder/blocks/fields/checkboxes_field_block.py
wagtail_advanced_form_builder/blocks/fields/condition_block.py
