Metadata-Version: 1.1
Name: wagtail-advanced-form-builder
Version: 1.0.0
Summary: Wagtail Advanced Form Builder
Home-page: https://github.com/octavenz/wagtail-advanced-form-builder
Author: Richard Blake (Octave)
Author-email: richard.blake@octave.nz
License: BSD
Platform: UNKNOWN
Classifier: Development Status :: 4 - Beta
Classifier: Intended Audience :: Developers
Classifier: License :: OSI Approved :: BSD License
Classifier: Operating System :: OS Independent
Classifier: Programming Language :: Python
Classifier: Programming Language :: Python :: 3
Classifier: Framework :: Wagtail :: 4
